[
  {
    "_id": {
      "$oid": "507f1f77bcf86cd799439021"
    },
    "order_code": "ORD-20240115-ABC123",
    "customer_name": "Rajesh Kumar",
    "customer_email": "rajesh.kumar@email.com",
    "customer_phone": "+91-9876543210",
    "package_id": {
      "$oid": "507f1f77bcf86cd799439011"
    },
    "status": "completed",
    "delivery_date": {
      "$date": "2024-01-16T00:00:00.000Z"
    },
    "story": "Birthday song for my wife on her 30th birthday",
    "music_style": "Romantic",
    "singer_voice": "Male",
    "mood": "Happy",
    "language": "Hindi",
    "special_message": "Happy Birthday Priya!",
    "reference_song": "Tum Hi Ho",
    "created_at": {
      "$date": "2024-01-15T10:30:00.000Z"
    },
    "updated_at": {
      "$date": "2024-01-16T14:00:00.000Z"
    }
  },
  {
    "_id": {
      "$oid": "507f1f77bcf86cd799439022"
    },
    "order_code": "ORD-20240125-DEF456",
    "customer_name": "Priya Sharma",
    "customer_email": "priya.sharma@email.com",
    "customer_phone": "+91-9876543211",
    "package_id": {
      "$oid": "507f1f77bcf86cd799439012"
    },
    "status": "processing",
    "delivery_date": {
      "$date": "2024-01-29T00:00:00.000Z"
    },
    "story": "Brand anthem for our startup TechFlow Solutions",
    "music_style": "Corporate",
    "singer_voice": "Mixed",
    "mood": "Motivational",
    "language": "English",
    "special_message": "Innovation drives us forward",
    "reference_song": "We Will Rock You",
    "created_at": {
      "$date": "2024-01-25T09:15:00.000Z"
    },
    "updated_at": {
      "$date": "2024-01-25T09:15:00.000Z"
    }
  },
  {
    "_id": {
      "$oid": "507f1f77bcf86cd799439023"
    },
    "order_code": "ORD-20240201-GHI789",
    "customer_name": "Amit Patel",
    "customer_email": "amit.patel@email.com",
    "customer_phone": "+91-9876543212",
    "package_id": {
      "$oid": "507f1f77bcf86cd799439013"
    },
    "status": "delivered",
    "delivery_date": {
      "$date": "2024-02-10T00:00:00.000Z"
    },
    "story": "College anthem for St. Xavier's College Mumbai",
    "music_style": "Institutional",
    "singer_voice": "Choral",
    "mood": "Proud",
    "language": "English",
    "special_message": "Excellence in education since 1869",
    "reference_song": "Gaudeamus Igitur",
    "created_at": {
      "$date": "2024-02-01T11:45:00.000Z"
    },
    "updated_at": {
      "$date": "2024-02-10T16:30:00.000Z"
    }
  },
  {
    "_id": {
      "$oid": "507f1f77bcf86cd799439024"
    },
    "order_code": "ORD-20240210-JKL012",
    "customer_name": "Sunita Gupta",
    "customer_email": "sunita.gupta@email.com",
    "customer_phone": "+91-9876543213",
    "package_id": {
      "$oid": "507f1f77bcf86cd799439011"
    },
    "status": "pending",
    "story": "Motivational song for my son's graduation",
    "music_style": "Pop",
    "singer_voice": "Female",
    "mood": "Inspirational",
    "language": "Hindi",
    "special_message": "Dream big, work hard, achieve more!",
    "reference_song": "Roar",
    "created_at": {
      "$date": "2024-02-10T08:20:00.000Z"
    },
    "updated_at": {
      "$date": "2024-02-10T08:20:00.000Z"
    }
  }
]